flask_hmin/__init__.py
flask_hmin/tool.py
Flask_Hmin-1.0.2.dist-info/LICENSE
Flask_Hmin-1.0.2.dist-info/METADATA
Flask_Hmin-1.0.2.dist-info/WHEEL
Flask_Hmin-1.0.2.dist-info/top_level.txt
Flask_Hmin-1.0.2.dist-info/RECORD
