Metadata-Version: 2.1
Name: Flask-Hmin
Version: 1.0.2
Summary: Flask压缩Html
Home-page: https://github.com/zhenzi0322/Flask-Hmin
Author: Long
Author-email: 82131529@qq.com
License: BSD-3-Clause
Platform: any
Classifier: Environment :: Web Environment
Classifier: Intended Audience :: Developers
Classifier: License :: OSI Approved :: BSD License
Classifier: Operating System :: OS Independent
Classifier: Programming Language :: Python
Classifier: Programming Language :: Python :: 3
Classifier: Programming Language :: Python :: 3.6
Classifier: Programming Language :: Python :: 3.7
Classifier: Programming Language :: Python :: 3.8
Classifier: Programming Language :: Python :: 3.9
Classifier: Topic :: Internet :: WWW/HTTP :: Dynamic Content
Classifier: Topic :: Software Development :: Libraries :: Python Modules
Classifier: Topic :: Text Processing :: Markup :: HTML
Requires-Python: >=3.6
License-File: LICENSE
Requires-Dist: Flask
Requires-Dist: htmlmin
Requires-Dist: redis
